{
  "Culture": "en",
  "Texts": {
    "Menu:Module": "Workflows",
    "Module:NotSelected": "Module Not Selected",
    "Module:Description": "Information about Workflows Module...",
    "Trace": "Trace",
    "Trace:Header": "Trace for \"{0}\"",
    "Trace:Actor:WaitingFor": "Waiting for {0}",
    "Trace:Actor:Reviewed": "Waiting for {0}. Reviewed at {1}",
    "Trace:Actor:Expected": "Expected {0}",
    "Trace:Actor:By": "by",
    "Trace:Actor:At": "at",
    "Trace:Actor:Approved": "Approved",
    "Trace:Actor:Rejected": "Rejected",
    "Approve:Success": "Successfuly approved!",
    "Reject": "Reject",
    "Reject:Success": "Successfuly rejected!",
    "Reject:Error": "Reject failed!",
    "Approve": "Approve",
    "Approve:Error": "Approve failed!",
    "WaitingFor": "Waiting for {0}",
    "CurrentState:None": "Enroute {0}",
    "CurrentState:Rejected": "Rejected by {0}",
    "CurrentState:Approved": "Approved {0}",
    "Search:Rows": "Search Rows",
    "States": "Steps",
    "States:Error": "Something went wrong with step.",
    "States:Details": "{0} Details",
    "States:Edit": "Steps",
    "States:Enabled": "Enabled",
    "States:NotSelected": "Step is not selected",
    "States:Added": "Step Added",
    "States:Removed": "Step Removed",
    "States:Add": "Add",
    "States:Name": "Name",
    "States:Name:Empty": "Name is empty",
    "States:ApprovalType": "Approval Type",
    "States:IsMandatory": "Is Mandatory",
    "States:IsReadOnly": "Is Readonly",
    "States:StateAlreadyInEditMode": "Some row is being edited. Please, save or cancel before proceeding.",
    "States:Actors:IsActive": "Is Active",
    "ApprovalType:Regular": "Ordered",
    "ApprovalType:Parallel": "Not Ordered",
    "ApprovalType:AtLeast": "At Least",
    "State:Actor": "Step Actor",
    "State:Actor:Edit": "Edit Actor",
    "States:Actors:Edit": "Actors",
    "States:Actors:Updated": "Step Actor Updated",
    "States:Actors:Selection": "Actor Selection",
    "States:Actors:Error": "Something went wrong with step actor.",
    "States:Actors:Reviewers": "Reviewers",
    "States:Actors:Reviewers:Add": "Add Reviewer",
    "States:Actors:ReviewersOf": "{0} Reviewers",
    "States:Actors:Approvers": "Approvers",
    "StatesGroup:Audit:UpdatedAt": "updated at {0} by {1}",
    "StatesGroup:Audit:New": "created at {0}",
    "StatesGroup:Audit:Enroute": "started at {0}",
    "StatesGroup:Audit:Complete": "completed at {0} by {1}",
    "StatesGroup:Audit:Canceled": "canceled at {0} by {1}",
    "LifecycleActorStatus:Canceled": "Canceled",
    "LifecycleActorStatus:Rejected": "Rejected",
    "LifecycleActorStatus:Approved": "Completed",
    "LifecycleActorStatus:Reviewed": "Reviewed",
    "LifecycleActorStatus:Enroute": "Waiting",
    "States:Actors:Cancelled": "has canceled at {0}",
    "States:Actors:Reviewed": "has reviewed at {0}",
    "States:Actors:Enroute": "Active",
    "States:Actors:Rejected": "has rejected at {0}",
    "States:Actors:Approved": "has approved at {0}",
    "LifecycleStatus:New": "New",
    "LifecycleStatus:Enroute": "Waiting",
    "LifecycleStatus:Active": "Active",
    "LifecycleStatus:Rejected": "Rejected",
    "LifecycleStatus:Complete": "Completed",
    "LifecycleStatus:Canceled": "Canceled",
    "LifecycleStatus:Unknown": "Unknown",
    "Trace:NotSupportedObjectType": "Trace not available for this object type",
    "Trace:NotAvailableForCurrentStatus": "Trace not available for current status",
    "States:Actors:Approvers:Add": "Add Approver",
    "States:Actors:ApproversOf": "{0} Approvers",
    "States:Actors:Name": "Actor Name",
    "States:Actors:Name:Empty": "Actor Name is empty",
    "States:Actors:Name:Invalid": "Actor Name cannot contain only spaces. Please enter a valid Actor Name.",
    "States:Actors:Save": "Save",
    "States:Actors:Type": "Type",
    "States:Actors:ActorType": "Actor Type",
    "States:Actors:Type:User": "User",
    "States:Actors:Type:User:Select": "Select User",
    "States:Actors:Type:Role": "Role",
    "States:Actors:Type:Role:Select": "Select Role",
    "States:Actors:Type:Initiator": "Initiator",
    "States:Actors:Type:Select": "Select Actor Type",
    "States:Actors:DisplayName": "Display Name",
    "States:Actors:FormAdmin": "Form Admin",
    "States:Actors:ApprovalAdmin": "Approval Admin",
    "States:Actors:ApprovalManager": "Approval Manager",
    "States:Actors:Enabled": "Enabled",
    "States:Actors:Add": "Add Actor",
    "States:Approvers:Add": "Add",
    "States:Actors:User:Select": "Select User",
    "States:Options": "Options",
    "StatesGroup": "Flow",
    "StatesGroup:Default": "Default",
    "StatesGroup:Default:CancelationError": "Can't disable or delete default flow. Try changing default flow first.",
    "StatesGroup:Error": "Something went wrong with flow.",
    "StatesGroup:States": "Workflow steps for '{0}'",
    "StatesGroup:Enabled": "Enabled",
    "StatesGroup:NotSelected": "Flow is not selected.",
    "DashboardPage:Reports:Title": "Reports",
    "DashboardPage:Workflows:Title": "Workflows",
    "StatesGroup:Add": "Add",
    "StatesGroup:Added": "Flow Added",
    "StatesGroup:Removed": "Flow Removed",
    "StatesGroup:Name": "Name",
    "StatesGroup:Name:Empty": "Name is empty",
    "StatesGroup:OrganizationUnits": "Organization Units",
    "StateGroups:StateGroupAlreadyInEditMode": "Some row is being edited. Please, save or cancel before proceeding.",
    "Selection:TaskList": "None",
    "Confirmation:Reject": "Rejection",
    "SaveSuccess": "Saved Successfully",
    "OrganizationUnit:ReassignmentError": "This organization unit is already assigned to another flow. Do you want to reassign it?",
    "ActorType:Initiator": "Initiator",
    "ActorType:Approver": "Approver",
    "ActorType:Reviewer": "Reviewer",
    "ApprovalNotification:Enroute": "Document {0} started EnRoute",
    "ApprovalNotification:Canceled": "Document {0} was canceled",
    "ApprovalNotification:Approved": "Document {0} was approved by {1}",
    "ApprovalNotification:Rejected": "Document {0} was rejected by {1}",
    "ApprovalNotification:ApprovalRequested": "Approval requested for document {0}",
    "ApprovalNotification:ApprovalRequestedByRole": "Approval requested for document {0} by role {1}",
    "Menu:Lifecycle": "Lifecycle",
    "Menu:Lifecycle:Workflows": "Workflows",
    "Menu:Lifecycle:Reports": "Reports",
    "DashboardPage:NoPendingDocumets": "No pending documents",
    "DashboardPage:Header:ExtraProperties": "Extra Properties",
    "DashboardPage:Header:Role": "Role",
    "DashboardPage:Header:StatusDate": "Status Date",
    "DashboardPage:Header:ModuleObjectType": "Doc Type",
    "DashboardPage:Header:CreatedAt": "Created At",
    "DashboardPage:Header:UpdatedAt": "Updated At",
    "DashboardPage:Header:UpdatedBy": "Updated By",
    "DashboardPage:Header:Groupname": "Workflow Name",
    "DashboardPage:Header:Status": "Status",
    "Lifecycle:PurchaseOrder": "Purchase Order Workflow",
    "Lifecycle:PurchaseRequest": "Purchase Request Workflow",
    "Lifecycle:RequestForProposal": "Request for Proposal Workflow",
    "Lifecycle:SupplyLine": "Supply Line Workflows",
    "Lifecycle:Production": "Production Workflows",
    "Lifecycle:SalesOrder": "Sales Order Workflows",
    "Lifecycle:GoodReceipt": "Good Receipt Workflows",
    "Lifecycle:LocalExpenseReport": "Local Expense Report Workflows",
    "Lifecycle:TravelExpenseReport": "Travel Expense Report Workflows",
    "Lifecycle:ReleasedItem": "Pick and Pack Workflows",
    "Lifecycle:TravelRequest": "Travel Request Workflows",
    "Lifecycle:APInvoice": "AP Invoice Workflows",
    "Lifecycle:Masav": "vPay Workflows",
    "Lifecycle:Inventory": "Inventory Workflows",
    "Lifecycle:Account": "Account Workflows",
    "Lifecycles": "Workflows",
    "Lifecycle:Items": "Purchase Items Workflows",
    "Lifecycle:SalesItems": "Sales Items Workflows",
    "Lifecycle:SalesRFP": "Sales RFP Workflows",
    "Lifecycle:SalesRequest": "Sales Request Workflows",
    "OrgUnitWasChangedWarning": "Organization Unit was changed. Save the request so that you can see the new flow?",
    "FlowNoAddedYet": "Flow for this request, no added yet. Do you want to save request?",
    "FlowForModuleNotCreated": "Flow for this request no added yet or doesn't have active steps/actors",
    "FlowWillChange": "Flow will change",
    "DefaultGroupChangeWarning": "Another flow is set as default. Do you want to reassign it?",
    "DeleteGroupWarning": "Are you sure you want to delete the {0} flow?",
    "States:Actors:ChooseActor": "Choose actor",
    "States:Actors:Type:Beneficiary": "Beneficiary",
    "States:Actors:Type:Beneficiary:Empty": "You should select a beneficiary",
    "States:Type": "Type",
    "States:Actors:Description": "Description",
    "States:Actors:Actor": "Actor",
    "States:Actors:Type:Empty": "You should select a type",
    "States:Actors:Type:User:Empty": "You should select a user",
    "States:Actors:Type:Role:Empty": "You should select a role",
    "Beneficiary": "Beneficiary",
    "States:Active": "Active",
    "States:AddSteps": "Add Step",
    "StatesGroup:Active": "Active",
    "AssignInActiveFlowToOrgUnit": "A unit can't be assigned to an inactive workflow.",
    "InActiveFlowSetDefaultGroupChangeWarning": "The flow is inactive. Do you want to activate it and set as default?",
    "States:Actors:Added": "Actor successfully added.",
    "States:Actors:Removed": "Actor successfully removed.",
    "States:Actors:Name:TooLong": "Description is too long. Please enter a short description",
    "StatesGroup:AddWorkflow": "Add",
    "AnyOrganizationUnit": "Any Organization Unit.",
    "StatesGroup:Default:RemoveError": "You can't delete default workflow.",
    "SetDefault": "Set as default",
    "Default": "Default",
    "DefaultWorkflowMsg": "This workflow is set as default for any organizational unit.",
    "States:Actors:ChooseRole": "Choose role",
    "States:NoStepsAddedYet": "No steps added yet",
    "NoWorkflowsAddedYet": "No workflows added yet",
    "Actors:NoReviewersAddedYet": "No reviewers added yet",
    "Actors:NoApproversAddedYet": "No approvers added yet",
    "StatesGroup:Type": "Type",
    "RejectedReason": "Rejected reason: {0}",
    "ApprovalFor": "approval for",
    "Month:LC": "month",
    "Months:LC": "months",
    "Year:LC": "year",
    "Years:LC": "years",
    "Day:LC": "day",
    "Days:LC": "days",
    "RejectedBy": "rejected by {0}",
    "Workflow:Canceled": "The workflow was canceled",
    "Workflow:New": "The workflow has not started yet",
    "Workflow:Approved": "The workflow approved at {0}",
    "Workflow:Rejected": "The workflow rejected by {0} at {1}",
    "Workflow:Ordered:Enroute": "Waiting for",
    "Approval": "approval",
    "For": "for",
    "Lifecycle:Vendor": "Vendor Workflows",
    "Lifecycle:Customer": "Customer Workflows",
    "Lifecycle:BusinessPartner": "Vendor Workflows",
    "States:StateNotSaved": "You should save step",
    "Permission:LifecycleFeatureModule": "Lifecycle",
    "Permission:LifecycleFeatureModule:General": "General",
    "Permission:LifecycleFeatureModule:LifecycleManager": "Lifecycle Manager",
    "Report:Details": "Report Details",
    "Report:Id": "Id",
    "Report:DocumentId": "Document Id",
    "Report:DocumentObjectType": "Document Object Type",
    "DocumentObjectType:{value}": "Document Object Type: {value}",
    "Report:CreationTime": "Creation Time",
    "Report:LastModificationTime": "Last Modification Time",
    "Report:LastModifierId": "Last Modifier Id",
    "Report:GroupName": "Group Name",
    "Report:Status": "Status",
    "Report:Role": "Role",
    "Report:StatusDate": "Status Date",
    "Report:ExtraProperties": "Extra Properties",
    "TraceCard:HistoryTitle": "Lifecycle trace",
    "TraceCard:TemplateTitle": "Lifecycle template"
  }
}
