{
  "Culture": "es",
  "Texts": {
    "SamplePageMessage": "Una página de muestra para el módulo Módulo",
    "Menu:Module": "MiNombreDeProyecto",
    "Menu:Top": "Programación de trabajos",
    "Menu:Triggers": "disparadores",
    "Menu:Tasks": "Tareas",
    "Menu:CreateTask": "Crear tarea",
    "AdminMenu:Top": "Programación de trabajos",
    "AdminMenu:ActionTypes": "Tipos de acción",
    "Tooltip:EditRow": "Editar fila",
    "Tooltip:RemoveRow": "Quitar fila",
    "Tooltip:SaveRow": "Guardar fila",
    "Tooltip:CanelRowEditing": "Cancelar la edición de filas",
    "ActionTypes:List:Title": "Tablero de tipos de acción",
    "ActionTypes:List:EmptyMessage": "No ha agregado ningún tipo de acción.",
    "ActionTypesSettings:HeaderTitle": "Parametros generales",
    "ActionTypesSettings:RowsTitle": "Tipos de configuración",
    "ActionTypesSettings:Title:New": "Nuevo tipo de acción",
    "ActionTypesSettings:Title:Edit": "Edición del tipo de acción '{0}'",
    "ActionTypes:AddActionType": "Agregar",
    "ActionType": "tipo de acción",
    "ActionType:UserFieldSet": "Conjunto de campos de configuración",
    "ActionType:DisplayName": "Nombre",
    "ActionType:ActionTypeCode": "Código",
    "ActionType:SourceDataSourceTypeId": "Tipo de fuente de datos",
    "ActionType:SourceDataSourceTypeName": "Tipo de fuente de datos",
    "ActionType:SourceActionType": "Tipos de acciones básicas",
    "ActionType:SourceDataSourceType": "Tipos de fuentes",
    "ActionType:DestinationDataSourceType": "Tipos de destino",
    "ActionType:IsDisabled": "Desactivado",
    "ActionType:IsDestinationRequired": "Destino Obligatorio",
    "ActionType:IsDestinationRequiredShort": "Requerido",
    "ActionTypes:TitleDetails": "Detalles",
    "ActionTypes:Error:SettingsFieldSetEmpty": "Debe seleccionar un conjunto de campos con configuraciones de acción.",
    "ActionTypes:Error:NameEmpty": "Debe especificar un nombre para mostrar para el tipo de acción.",
    "ActionTypes:Error:SourceEmpty": "Debe seleccionar un tipo de fuente de datos de origen.",
    "ActionTypes:Error:DestinationEmpty": "Debe seleccionar un tipo de fuente de datos de destino.",
    "ActionTypes:Enabled": "Activado",
    "ActionSettingType:Name": "Nombre",
    "ActionSettingType:DefaultValue": "Valor por defecto",
    "ActionSettingType:Type": "Tipo",
    "ActionSettingType:IsRequired": "Requerido",
    "ActionSettingTypes:Empty": "No ha agregado ningún tipo de configuración.",
    "ActionSettingTypes:Add:Tooltip": "Agregar nuevo tipo de configuración",
    "ActionSettingTypes:Add": "Agregar",
    "ActionSettingTypes:Title": "Configuración del tipo de acción",
    "Error:RowEditingInProcess": "Ya está editando una fila. Por favor, termina de editarlo primero.",
    "ActionSettingTypes:Errors:NameEmpty": "Debe especificar un nombre para el tipo de configuración.",
    "ActionSettingTypes:Errors:DefaultValueEmpty": "Al editar un tipo de acción existente, debe especificar un valor predeterminado para el tipo de configuración.",
    "ActionSettingTypes:Errors:TypeEmpty": "Debe especificar un tipo para el tipo de configuración.",
    "Trigger:Name": "Nombre",
    "Trigger:IsEnabled": "Activado",
    "Trigger:Start": "Empieza a",
    "Trigger:Expire": "Caduca a las",
    "Trigger:Period": "Se repite cada",
    "Trigger:PeriodType": "Ocurre",
    "Trigger:DaysOfWeek": "Días de la semana",
    "Trigger:DaysOfMonth": "dias del mes",
    "Trigger:Months": "Meses",
    "Trigger:Summary": "Resumen",
    "Triggers:TitleDetails": "Detalles",
    "Triggers:List:EmptyMessage": "No ha agregado ningún disparador.",
    "Triggers:Selection:Title": "Seleccionar disparadores de tareas",
    "TriggersSettings:Title:Edit": "Activador de edición '{0}'",
    "TriggersSettings:Title:New": "Creando un nuevo disparador",
    "TriggersSettings:Settings": "Ajustes",
    "TriggersSettings:AdvancedSettings": "Ajustes avanzados",
    "RepeatEvery": "Repite cada",
    "ForDurationOf": "Por una duración de",
    "On": "En",
    "UpTo": "Hasta",
    "Times": "Veces",
    "Occurs": "Ocurre",
    "PeriodType:OneTime": "Una vez",
    "PeriodType:Daily": "A diario",
    "PeriodType:Weekly": "Semanalmente",
    "PeriodType:Monthly": "Mensual",
    "5Minutes": "5 minutos",
    "10Minutes": "10 minutos",
    "15Minutes": "15 minutos",
    "30Minutes": "30 minutos",
    "1Hour": "1 hora",
    "6Hours": "6 horas",
    "12Hours": "12 horas",
    "1Day": "1 día",
    "3Days": "3 días",
    "7Days": "7 días",
    "14Days": "14 dias",
    "28Days": "28 días",
    "Hours": "Horas",
    "Days": "Días",
    "DaysOfWeek": "Días de la semana",
    "Weeks": "Semanas",
    "Months": "Meses",
    "Trigger:DayOfWeekOccurence:1": "Primero",
    "Trigger:DayOfWeekOccurence:2": "Segundo",
    "Trigger:DayOfWeekOccurence:3": "Tercero",
    "Trigger:DayOfWeekOccurence:4": "Cuatro",
    "Trigger:DayOfWeek:1": "Lunes",
    "Trigger:DayOfWeek:2": "Martes",
    "Trigger:DayOfWeek:3": "Miércoles",
    "Trigger:DayOfWeek:4": "Jueves",
    "Trigger:DayOfWeek:5": "Viernes",
    "Trigger:DayOfWeek:6": "Sábado",
    "Trigger:DayOfWeek:7": "Domingo",
    "Trigger:Month:1": "Enero",
    "Trigger:Month:2": "Febrero",
    "Trigger:Month:3": "Marzo",
    "Trigger:Month:4": "Abril",
    "Trigger:Month:5": "Puede",
    "Trigger:Month:6": "Junio",
    "Trigger:Month:7": "Julio",
    "Trigger:Month:8": "Agosto",
    "Trigger:Month:9": "Septiembre",
    "Trigger:Month:10": "Octubre",
    "Trigger:Month:11": "Noviembre",
    "Trigger:Month:12": "Diciembre",
    "Last": "Último",
    "Triggers:AddTrigger": "Agregar",
    "Triggers": "disparadores",
    "Triggers:List:Title": "Panel de disparadores",
    "Triggers:SaveSuccess": "Activador guardado con éxito.",
    "Triggers:SaveFail": "Trigger save falló.",
    "Triggers:SaveError": "Ocurrió un error al guardar el disparador.",
    "Triggers:ConfirmUpdate": "Hay algunas tareas que están vinculadas a este disparador. ¿Quieres actualizarlos ahora?",
    "Triggers:Errors:NameEmpty": "Debe especificar un nombre para el activador.",
    "Triggers:Errors:StartEmpty": "Debe especificar una fecha de inicio para el disparador.",
    "Triggers:Errors:ExpireEmpty": "Debe especificar una fecha de caducidad para el disparador.",
    "Triggers:Errors:RepeatDurationEmpty": "Debe especificar una duración de repetición para el activador o desmarcarlo.",
    "Triggers:Errors:RepeatIntervalEmpty": "Debe especificar un intervalo de repetición para el disparador o desmarcarlo.",
    "Triggers:Errors:PeriodEmpty": "Debe especificar un período para el activador.",
    "Triggers:Errors:DaysOfWeekEmpty": "Debe elegir al menos un día de la semana.",
    "Triggers:Errors:MonthsEmpty": "Debe elegir al menos un mes.",
    "Triggers:Errors:DaysOfMonthEmpty": "Debe elegir al menos un día del mes.",
    "Triggers:Errors:DaysOfWeekOccurenceEmpty": "Debe elegir al menos un día de la semana de ocurrencia.",
    "Task:AllowForceStop": "Forzar la tarea para que se detenga si se solicita",
    "Task:RunAsapOnMisfire": "Ejecutar la tarea lo antes posible después de un inicio programado perdido",
    "Task:AllowToBeRunOnDemand": "Permitir que se ejecute bajo demanda",
    "Task:IsActive": "Activo",
    "Task:Description": "Descripción",
    "Task:Name": "Nombre",
    "Task:LastManualRunTime": "Última ejecución manual",
    "Task:NoLastManualRunTime": "Todavía no se ejecutó manualmente'",
    "Task:LastRunTime": "Última ejecución programada",
    "Task:NoLastRunTime": "aún no se ejecutó",
    "Task:NextRunTime": "Próxima ejecución programada",
    "Task:NoNextRunTime": "No programada",
    "Task:Status": "Estado",
    "Tasks:EditTask:Tooltip": "Editar tarea",
    "Tasks:EditTriggers": "Seleccionar disparadores",
    "Tasks:SaveTriggersEdit": "Seleccionar",
    "Tasks:CancelTriggersEdit": "Cancelar",
    "Tasks:NoTriggersSelected": "No ha seleccionado ningún disparador.",
    "Tasks:NoTriggersAvailable": "No hay disparadores disponibles. Agregue algunos usando el menú correspondiente.",
    "Tasks:AfterFailRepeatEvery": "Después de fallar repetir cada",
    "Tasks:DeleteIfNotScheduledFor": "Si la tarea no estaba programada, elimínela después",
    "Tasks:TimeoutAfter": "Detener la tarea si dura más de",
    "Tasks:CreateTask": "Crear tarea",
    "Tasks:Settings": "Ajustes",
    "Tasks:History": "Historia",
    "Tasks:Title:New": "Creando nueva tarea",
    "Tasks:Title:Edit": "Detalles de la Tarea {0}",
    "Tasks:Title:List": "Panel de tareas",
    "Tasks:SaveSuccess": "Tarea guardada con éxito.",
    "Tasks:SaveFail": "No se pudo guardar la tarea.",
    "Tasks:SaveError": "Ocurrió un error al guardar la tarea",
    "Tasks:Run": "Correr",
    "Tasks:Run:Confirm": "¿Quieres ejecutar la tarea?",
    "Tasks:Run:Tooltip": "Ejecutar tarea",
    "Tasks:RunSuccess": "Tarea ejecutada con éxito.",
    "Tasks:RunFail": "La ejecución de la tarea falló.",
    "Tasks:RunError": "Se produjo un error al intentar ejecutar taks.",
    "Tasks:CanNotBeRun": "La tarea debe estar 'Lista' y debe permitirse la ejecución manual",
    "Tasks:IsRunning": "La tarea se está ejecutando",
    "Tasks:Errors:IsInactive": "La tarea está inactiva.",
    "Tasks:Errors:AlreadyRunning": "La tarea ya se está ejecutando.",
    "Tasks:Errors:NameEmpty": "Debe especificar un nombre para la tarea.",
    "Tasks:Errors:RestartMaxAttemptsEmpty": "Debe especificar un recuento máximo de intentos de reinicio o deshabilitar la configuración",
    "Tasks:Errors:ActionsEmpty": "Debes agregar al menos una acción.",
    "TaskStatus:Inactive": "Inactivo",
    "TaskStatus:Ready": "Listo",
    "TaskStatus:Running": "Correr",
    "TaskExecution:Status": "Estado",
    "TaskExecution:RunnedByUserName": "Contener",
    "TaskExecution:LastRunTime": "Última carrera",
    "TaskExecutions:NoTaskExecutions": "La tarea aún no se ejecutó",
    "TaskExecutionStatus:Initializing": "Inicializando",
    "TaskExecutionStatus:Executing": "ejecutando",
    "TaskExecutionStatus:Failed": "Fallido",
    "TaskExecutionStatus:Completed": "Terminado",
    "ActionExecution:ActionTypeCode": "tipo de acción",
    "ActionExecution:ActionName": "Nombre de la acción",
    "ActionExecution:StartedAt": "Empezó a las",
    "ActionExecution:CompletedAt": "completado en",
    "ActionExecution:Status": "Estado",
    "ActionExecutionStatus:NotStarted": "No empezado",
    "ActionExecutionStatus:Initializing": "Inicializando",
    "ActionExecutionStatus:Executing": "ejecutando",
    "ActionExecutionStatus:Failed": "Fallido",
    "ActionExecutionStatus:Completed": "Terminado",
    "Actions": "Comportamiento",
    "Action:DisplayName": "Nombre para mostrar",
    "Action:ActionTypeCode": "Código de tipo",
    "Action:SourceDataSource": "Fuente",
    "Action:SourceAction": "Acción de origen",
    "Action:DestinationDataSource": "Destino",
    "Actions:NoActions": "No has añadido ninguna acción.",
    "Actions:SelectActionTypeFirst": "Seleccione Tipo de acción primero",
    "Actions:AddAction": "Añadir acción",
    "Actions:Settings": "Ajustes",
    "Actions:Settings:Create": "Crear nueva acción",
    "Actions:Settings:Edit": "Edición de la acción '{0}'",
    "Actions:Settings:Cancel": "Cancelar",
    "Actions:EditAction:Tooltip": "Editar acción",
    "Actions:RemoveAction:Tooltip": "Quitar acción",
    "Actions:DestinationNotRequired": "El destino no es obligatorio para este tipo de acción",
    "Actions:Errors:NameEmpty": "Debe especificar un nombre para mostrar",
    "Actions:Errors:ActionTypeNotSelected": "Debe seleccionar un tipo de acción",
    "Actions:Errors:SourceNotSelected": "Debe seleccionar una fuente",
    "Actions:Errors:DestinationNotSelected": "Debes seleccionar un destino",
    "Actions:Errors:SourcesShouldBeBefore": "Esta fila debe colocarse solo después de sus fuentes.",
    "Actions:Errors:CanNotDeleteParent": "No se puede eliminar porque las siguientes acciones utilizan la acción como fuente: {0}",
    "ActionSetting:Name": "Nombre",
    "ActionSetting:Value": "Valor",
    "ActionSetting:Type": "Tipo",
    "ActionSettings:Add": "Agregar",
    "ActionSettings:Add:Tooltip": "Agregar configuración",
    "ActionSettings:Empty": "No hay ajustes para esta acción.",
    "ActionSettings:NotRelevant": "Irrelevante",
    "ActionSettings:Errors:ValueEmpty": "El valor de configuración no puede estar vacío"
  }
}